[
    {
        "model": "metro.Station",
        "pk": 1,
        "fields": {
            "name_station": "Бульвар Рокоссовского",
            "name_line": "1",
            "id": "1",
            "id_line": "1"
        }
    },
    {
        "model": "metro.Station",
        "pk": 2,
        "fields": {
            "name_station": "Черкизовская",
            "name_line": "1",
            "id": "2",
            "id_line": "1"
        }
    },
    {
        "model": "metro.Station",
        "pk": 3,
        "fields": {
            "name_station": "Преображенская площадь",
            "name_line": "1",
            "id": "3",
            "id_line": "1"
        }
    },
    {
        "model": "metro.Station",
        "pk": 4,
        "fields": {
            "name_station": "Сокольники",
            "name_line": "1",
            "id": "4",
            "id_line": "1"
        }
    },
    {
        "model": "metro.Station",
        "pk": 5,
        "fields": {
            "name_station": "Красносельская",
            "name_line": "1",
            "id": "5",
            "id_line": "1"
        }
    },
    {
        "model": "metro.Station",
        "pk": 6,
        "fields": {
            "name_station": "Комсомольская СЛ",
            "name_line": "1",
            "id": "6",
            "id_line": "1"
        }
    },
    {
        "model": "metro.Station",
        "pk": 7,
        "fields": {
            "name_station": "Красные ворота",
            "name_line": "1",
            "id": "7",
            "id_line": "1"
        }
    },
    {
        "model": "metro.Station",
        "pk": 8,
        "fields": {
            "name_station": "Чистые пруды",
            "name_line": "1",
            "id": "8",
            "id_line": "1"
        }
    },
    {
        "model": "metro.Station",
        "pk": 9,
        "fields": {
            "name_station": "Лубянка",
            "name_line": "1",
            "id": "9",
            "id_line": "1"
        }
    },
    {
        "model": "metro.Station",
        "pk": 10,
        "fields": {
            "name_station": "Охотный ряд",
            "name_line": "1",
            "id": "10",
            "id_line": "1"
        }
    },
    {
        "model": "metro.Station",
        "pk": 11,
        "fields": {
            "name_station": "Библиотека имени Ленина",
            "name_line": "1",
            "id": "11",
            "id_line": "1"
        }
    },
    {
        "model": "metro.Station",
        "pk": 12,
        "fields": {
            "name_station": "Кропоткинская",
            "name_line": "1",
            "id": "12",
            "id_line": "1"
        }
    },
    {
        "model": "metro.Station",
        "pk": 13,
        "fields": {
            "name_station": "Парк культуры СЛ",
            "name_line": "1",
            "id": "13",
            "id_line": "1"
        }
    },
    {
        "model": "metro.Station",
        "pk": 14,
        "fields": {
            "name_station": "Фрунзенская",
            "name_line": "1",
            "id": "14",
            "id_line": "1"
        }
    },
    {
        "model": "metro.Station",
        "pk": 15,
        "fields": {
            "name_station": "Спортивная",
            "name_line": "1",
            "id": "15",
            "id_line": "1"
        }
    },
    {
        "model": "metro.Station",
        "pk": 16,
        "fields": {
            "name_station": "Воробьёвы горы",
            "name_line": "1",
            "id": "16",
            "id_line": "1"
        }
    },
    {
        "model": "metro.Station",
        "pk": 17,
        "fields": {
            "name_station": "Университет",
            "name_line": "1",
            "id": "17",
            "id_line": "1"
        }
    },
    {
        "model": "metro.Station",
        "pk": 18,
        "fields": {
            "name_station": "Проспект Вернадского",
            "name_line": "1",
            "id": "18",
            "id_line": "1"
        }
    },
    {
        "model": "metro.Station",
        "pk": 19,
        "fields": {
            "name_station": "Юго-Западная",
            "name_line": "1",
            "id": "19",
            "id_line": "1"
        }
    },
    {
        "model": "metro.Station",
        "pk": 20,
        "fields": {
            "name_station": "Тропарёво",
            "name_line": "1",
            "id": "20",
            "id_line": "1"
        }
    },
    {
        "model": "metro.Station",
        "pk": 21,
        "fields": {
            "name_station": "Румянцево",
            "name_line": "1",
            "id": "21",
            "id_line": "1"
        }
    },
    {
        "model": "metro.Station",
        "pk": 22,
        "fields": {
            "name_station": "Саларьево",
            "name_line": "1",
            "id": "22",
            "id_line": "1"
        }
    },
    {
        "model": "metro.Station",
        "pk": 23,
        "fields": {
            "name_station": "Филатов Луг",
            "name_line": "1",
            "id": "266",
            "id_line": "1"
        }
    },
    {
        "model": "metro.Station",
        "pk": 24,
        "fields": {
            "name_station": "Прокшино",
            "name_line": "1",
            "id": "267",
            "id_line": "1"
        }
    },
    {
        "model": "metro.Station",
        "pk": 25,
        "fields": {
            "name_station": "Ольховая",
            "name_line": "1",
            "id": "268",
            "id_line": "1"
        }
    },
    {
        "model": "metro.Station",
        "pk": 26,
        "fields": {
            "name_station": "Коммунарка",
            "name_line": "1",
            "id": "269",
            "id_line": "1"
        }
    },
    {
        "model": "metro.Station",
        "pk": 27,
        "fields": {
            "name_station": "Ховрино",
            "name_line": "2",
            "id": "244",
            "id_line": "2"
        }
    },
    {
        "model": "metro.Station",
        "pk": 28,
        "fields": {
            "name_station": "Беломорская",
            "name_line": "2",
            "id": "260",
            "id_line": "2"
        }
    },
    {
        "model": "metro.Station",
        "pk": 29,
        "fields": {
            "name_station": "Речной вокзал",
            "name_line": "2",
            "id": "23",
            "id_line": "2"
        }
    },
    {
        "model": "metro.Station",
        "pk": 30,
        "fields": {
            "name_station": "Водный стадион",
            "name_line": "2",
            "id": "24",
            "id_line": "2"
        }
    },
    {
        "model": "metro.Station",
        "pk": 31,
        "fields": {
            "name_station": "Войковская",
            "name_line": "2",
            "id": "25",
            "id_line": "2"
        }
    },
    {
        "model": "metro.Station",
        "pk": 32,
        "fields": {
            "name_station": "Сокол",
            "name_line": "2",
            "id": "26",
            "id_line": "2"
        }
    },
    {
        "model": "metro.Station",
        "pk": 33,
        "fields": {
            "name_station": "Аэропорт",
            "name_line": "2",
            "id": "27",
            "id_line": "2"
        }
    },
    {
        "model": "metro.Station",
        "pk": 34,
        "fields": {
            "name_station": "Динамо",
            "name_line": "2",
            "id": "28",
            "id_line": "2"
        }
    },
    {
        "model": "metro.Station",
        "pk": 35,
        "fields": {
            "name_station": "Белорусская ЗЛ",
            "name_line": "2",
            "id": "29",
            "id_line": "2"
        }
    },
    {
        "model": "metro.Station",
        "pk": 36,
        "fields": {
            "name_station": "Маяковская",
            "name_line": "2",
            "id": "30",
            "id_line": "2"
        }
    },
    {
        "model": "metro.Station",
        "pk": 37,
        "fields": {
            "name_station": "Тверская",
            "name_line": "2",
            "id": "31",
            "id_line": "2"
        }
    },
    {
        "model": "metro.Station",
        "pk": 38,
        "fields": {
            "name_station": "Театральная",
            "name_line": "2",
            "id": "32",
            "id_line": "2"
        }
    },
    {
        "model": "metro.Station",
        "pk": 39,
        "fields": {
            "name_station": "Новокузнецкая",
            "name_line": "2",
            "id": "33",
            "id_line": "2"
        }
    },
    {
        "model": "metro.Station",
        "pk": 40,
        "fields": {
            "name_station": "Павелецкая ЗЛ",
            "name_line": "2",
            "id": "34",
            "id_line": "2"
        }
    },
    {
        "model": "metro.Station",
        "pk": 41,
        "fields": {
            "name_station": "Автозаводская",
            "name_line": "2",
            "id": "35",
            "id_line": "2"
        }
    },
    {
        "model": "metro.Station",
        "pk": 42,
        "fields": {
            "name_station": "Технопарк",
            "name_line": "2",
            "id": "36",
            "id_line": "2"
        }
    },
    {
        "model": "metro.Station",
        "pk": 43,
        "fields": {
            "name_station": "Коломенская",
            "name_line": "2",
            "id": "37",
            "id_line": "2"
        }
    },
    {
        "model": "metro.Station",
        "pk": 44,
        "fields": {
            "name_station": "Каширская ЗЛ",
            "name_line": "2",
            "id": "38",
            "id_line": "2"
        }
    },
    {
        "model": "metro.Station",
        "pk": 45,
        "fields": {
            "name_station": "Кантемировская",
            "name_line": "2",
            "id": "39",
            "id_line": "2"
        }
    },
    {
        "model": "metro.Station",
        "pk": 46,
        "fields": {
            "name_station": "Царицыно",
            "name_line": "2",
            "id": "40",
            "id_line": "2"
        }
    },
    {
        "model": "metro.Station",
        "pk": 47,
        "fields": {
            "name_station": "Орехово",
            "name_line": "2",
            "id": "41",
            "id_line": "2"
        }
    },
    {
        "model": "metro.Station",
        "pk": 48,
        "fields": {
            "name_station": "Домодедовская",
            "name_line": "2",
            "id": "42",
            "id_line": "2"
        }
    },
    {
        "model": "metro.Station",
        "pk": 49,
        "fields": {
            "name_station": "Красногвардейская",
            "name_line": "2",
            "id": "43",
            "id_line": "2"
        }
    },
    {
        "model": "metro.Station",
        "pk": 50,
        "fields": {
            "name_station": "Алма-Атинская",
            "name_line": "2",
            "id": "44",
            "id_line": "2"
        }
    },
    {
        "model": "metro.Station",
        "pk": 51,
        "fields": {
            "name_station": "Пятницкое шоссе",
            "name_line": "3",
            "id": "45",
            "id_line": "3"
        }
    },
    {
        "model": "metro.Station",
        "pk": 52,
        "fields": {
            "name_station": "Митино",
            "name_line": "3",
            "id": "46",
            "id_line": "3"
        }
    },
    {
        "model": "metro.Station",
        "pk": 53,
        "fields": {
            "name_station": "Волоколамская",
            "name_line": "3",
            "id": "47",
            "id_line": "3"
        }
    },
    {
        "model": "metro.Station",
        "pk": 54,
        "fields": {
            "name_station": "Мякинино",
            "name_line": "3",
            "id": "48",
            "id_line": "3"
        }
    },
    {
        "model": "metro.Station",
        "pk": 55,
        "fields": {
            "name_station": "Строгино",
            "name_line": "3",
            "id": "49",
            "id_line": "3"
        }
    },
    {
        "model": "metro.Station",
        "pk": 56,
        "fields": {
            "name_station": "Крылатское",
            "name_line": "3",
            "id": "50",
            "id_line": "3"
        }
    },
    {
        "model": "metro.Station",
        "pk": 57,
        "fields": {
            "name_station": "Молодёжная",
            "name_line": "3",
            "id": "51",
            "id_line": "3"
        }
    },
    {
        "model": "metro.Station",
        "pk": 58,
        "fields": {
            "name_station": "Кунцевская АПЛ",
            "name_line": "3",
            "id": "52",
            "id_line": "3"
        }
    },
    {
        "model": "metro.Station",
        "pk": 59,
        "fields": {
            "name_station": "Славянский бульвар",
            "name_line": "3",
            "id": "53",
            "id_line": "3"
        }
    },
    {
        "model": "metro.Station",
        "pk": 60,
        "fields": {
            "name_station": "Парк победы АПЛ",
            "name_line": "3",
            "id": "54",
            "id_line": "3"
        }
    },
    {
        "model": "metro.Station",
        "pk": 61,
        "fields": {
            "name_station": "Киевская АПЛ",
            "name_line": "3",
            "id": "55",
            "id_line": "3"
        }
    },
    {
        "model": "metro.Station",
        "pk": 62,
        "fields": {
            "name_station": "Смоленская АПЛ",
            "name_line": "3",
            "id": "56",
            "id_line": "3"
        }
    },
    {
        "model": "metro.Station",
        "pk": 63,
        "fields": {
            "name_station": "Арбатская АПЛ",
            "name_line": "3",
            "id": "57",
            "id_line": "3"
        }
    },
    {
        "model": "metro.Station",
        "pk": 64,
        "fields": {
            "name_station": "Площадь революции",
            "name_line": "3",
            "id": "58",
            "id_line": "3"
        }
    },
    {
        "model": "metro.Station",
        "pk": 65,
        "fields": {
            "name_station": "Курская АПЛ",
            "name_line": "3",
            "id": "59",
            "id_line": "3"
        }
    },
    {
        "model": "metro.Station",
        "pk": 66,
        "fields": {
            "name_station": "Бауманская",
            "name_line": "3",
            "id": "60",
            "id_line": "3"
        }
    },
    {
        "model": "metro.Station",
        "pk": 67,
        "fields": {
            "name_station": "Электрозаводская",
            "name_line": "3",
            "id": "61",
            "id_line": "3"
        }
    },
    {
        "model": "metro.Station",
        "pk": 68,
        "fields": {
            "name_station": "Семёновская",
            "name_line": "3",
            "id": "62",
            "id_line": "3"
        }
    },
    {
        "model": "metro.Station",
        "pk": 69,
        "fields": {
            "name_station": "Партизанская",
            "name_line": "3",
            "id": "63",
            "id_line": "3"
        }
    },
    {
        "model": "metro.Station",
        "pk": 70,
        "fields": {
            "name_station": "Измайловская",
            "name_line": "3",
            "id": "64",
            "id_line": "3"
        }
    },
    {
        "model": "metro.Station",
        "pk": 71,
        "fields": {
            "name_station": "Первомайская",
            "name_line": "3",
            "id": "65",
            "id_line": "3"
        }
    },
    {
        "model": "metro.Station",
        "pk": 72,
        "fields": {
            "name_station": "Щёлковская",
            "name_line": "3",
            "id": "66",
            "id_line": "3"
        }
    },
    {
        "model": "metro.Station",
        "pk": 73,
        "fields": {
            "name_station": "Кунцевская ФЛ",
            "name_line": "4",
            "id": "67",
            "id_line": "4"
        }
    },
    {
        "model": "metro.Station",
        "pk": 74,
        "fields": {
            "name_station": "Пионерская",
            "name_line": "4",
            "id": "68",
            "id_line": "4"
        }
    },
    {
        "model": "metro.Station",
        "pk": 75,
        "fields": {
            "name_station": "Филёвский парк",
            "name_line": "4",
            "id": "69",
            "id_line": "4"
        }
    },
    {
        "model": "metro.Station",
        "pk": 76,
        "fields": {
            "name_station": "Багратионовская",
            "name_line": "4",
            "id": "70",
            "id_line": "4"
        }
    },
    {
        "model": "metro.Station",
        "pk": 77,
        "fields": {
            "name_station": "Фили",
            "name_line": "4",
            "id": "71",
            "id_line": "4"
        }
    },
    {
        "model": "metro.Station",
        "pk": 78,
        "fields": {
            "name_station": "Кутузовская",
            "name_line": "4",
            "id": "72",
            "id_line": "4"
        }
    },
    {
        "model": "metro.Station",
        "pk": 79,
        "fields": {
            "name_station": "Студенческая",
            "name_line": "4",
            "id": "73",
            "id_line": "4"
        }
    },
    {
        "model": "metro.Station",
        "pk": 80,
        "fields": {
            "name_station": "Киевская ФЛ",
            "name_line": "4",
            "id": "74",
            "id_line": "4"
        }
    },
    {
        "model": "metro.Station",
        "pk": 81,
        "fields": {
            "name_station": "Смоленская ФЛ",
            "name_line": "4",
            "id": "77",
            "id_line": "4"
        }
    },
    {
        "model": "metro.Station",
        "pk": 82,
        "fields": {
            "name_station": "Арбатская ФЛ",
            "name_line": "4",
            "id": "78",
            "id_line": "4"
        }
    },
    {
        "model": "metro.Station",
        "pk": 83,
        "fields": {
            "name_station": "Александровский сад",
            "name_line": "4",
            "id": "79",
            "id_line": "4"
        }
    },
    {
        "model": "metro.Station",
        "pk": 84,
        "fields": {
            "name_station": "Москва-Сити ФЛ",
            "name_line": "4А",
            "id": "450",
            "id_line": "4"
        }
    },
    {
        "model": "metro.Station",
        "pk": 85,
        "fields": {
            "name_station": "Деловой центр ФЛ",
            "name_line": "4А",
            "id": "449",
            "id_line": "4"
        }
    },
    {
        "model": "metro.Station",
        "pk": 86,
        "fields": {
            "name_station": "Киевская ФЛ",
            "name_line": "4А",
            "id": "74",
            "id_line": "4"
        }
    },
    {
        "model": "metro.Station",
        "pk": 87,
        "fields": {
            "name_station": "Смоленская ФЛ",
            "name_line": "4А",
            "id": "77",
            "id_line": "4"
        }
    },
    {
        "model": "metro.Station",
        "pk": 88,
        "fields": {
            "name_station": "Арбатская ФЛ",
            "name_line": "4А",
            "id": "78",
            "id_line": "4"
        }
    },
    {
        "model": "metro.Station",
        "pk": 89,
        "fields": {
            "name_station": "Александровский сад",
            "name_line": "4А",
            "id": "79",
            "id_line": "4"
        }
    },
    {
        "model": "metro.Station",
        "pk": 90,
        "fields": {
            "name_station": "Комсомольская КЛ",
            "name_line": "5",
            "id": "80",
            "id_line": "5"
        }
    },
    {
        "model": "metro.Station",
        "pk": 91,
        "fields": {
            "name_station": "Курская КЛ",
            "name_line": "5",
            "id": "81",
            "id_line": "5"
        }
    },
    {
        "model": "metro.Station",
        "pk": 92,
        "fields": {
            "name_station": "Таганская КЛ",
            "name_line": "5",
            "id": "82",
            "id_line": "5"
        }
    },
    {
        "model": "metro.Station",
        "pk": 93,
        "fields": {
            "name_station": "Павелецкая КЛ",
            "name_line": "5",
            "id": "83",
            "id_line": "5"
        }
    },
    {
        "model": "metro.Station",
        "pk": 94,
        "fields": {
            "name_station": "Добрынинская",
            "name_line": "5",
            "id": "84",
            "id_line": "5"
        }
    },
    {
        "model": "metro.Station",
        "pk": 95,
        "fields": {
            "name_station": "Октябрьская КЛ",
            "name_line": "5",
            "id": "85",
            "id_line": "5"
        }
    },
    {
        "model": "metro.Station",
        "pk": 96,
        "fields": {
            "name_station": "Парк культуры КЛ",
            "name_line": "5",
            "id": "86",
            "id_line": "5"
        }
    },
    {
        "model": "metro.Station",
        "pk": 97,
        "fields": {
            "name_station": "Киевская КЛ",
            "name_line": "5",
            "id": "87",
            "id_line": "5"
        }
    },
    {
        "model": "metro.Station",
        "pk": 98,
        "fields": {
            "name_station": "Краснопресненская",
            "name_line": "5",
            "id": "88",
            "id_line": "5"
        }
    },
    {
        "model": "metro.Station",
        "pk": 99,
        "fields": {
            "name_station": "Белорусская КЛ",
            "name_line": "5",
            "id": "89",
            "id_line": "5"
        }
    },
    {
        "model": "metro.Station",
        "pk": 100,
        "fields": {
            "name_station": "Новослободская",
            "name_line": "5",
            "id": "90",
            "id_line": "5"
        }
    },
    {
        "model": "metro.Station",
        "pk": 101,
        "fields": {
            "name_station": "Проспект мира КЛ",
            "name_line": "5",
            "id": "91",
            "id_line": "5"
        }
    },
    {
        "model": "metro.Station",
        "pk": 102,
        "fields": {
            "name_station": "Комсомольская КЛ",
            "name_line": "5",
            "id": "80",
            "id_line": "5"
        }
    },
    {
        "model": "metro.Station",
        "pk": 103,
        "fields": {
            "name_station": "Медведково",
            "name_line": "6",
            "id": "92",
            "id_line": "6"
        }
    },
    {
        "model": "metro.Station",
        "pk": 104,
        "fields": {
            "name_station": "Бабушкинская",
            "name_line": "6",
            "id": "93",
            "id_line": "6"
        }
    },
    {
        "model": "metro.Station",
        "pk": 105,
        "fields": {
            "name_station": "Свиблово",
            "name_line": "6",
            "id": "94",
            "id_line": "6"
        }
    },
    {
        "model": "metro.Station",
        "pk": 106,
        "fields": {
            "name_station": "Ботанический сад",
            "name_line": "6",
            "id": "95",
            "id_line": "6"
        }
    },
    {
        "model": "metro.Station",
        "pk": 107,
        "fields": {
            "name_station": "ВДНХ",
            "name_line": "6",
            "id": "96",
            "id_line": "6"
        }
    },
    {
        "model": "metro.Station",
        "pk": 108,
        "fields": {
            "name_station": "Алексеевская",
            "name_line": "6",
            "id": "97",
            "id_line": "6"
        }
    },
    {
        "model": "metro.Station",
        "pk": 109,
        "fields": {
            "name_station": "Рижская",
            "name_line": "6",
            "id": "98",
            "id_line": "6"
        }
    },
    {
        "model": "metro.Station",
        "pk": 110,
        "fields": {
            "name_station": "Проспект Мира КРЛ",
            "name_line": "6",
            "id": "99",
            "id_line": "6"
        }
    },
    {
        "model": "metro.Station",
        "pk": 111,
        "fields": {
            "name_station": "Сухаревская",
            "name_line": "6",
            "id": "100",
            "id_line": "6"
        }
    },
    {
        "model": "metro.Station",
        "pk": 112,
        "fields": {
            "name_station": "Тургеневская",
            "name_line": "6",
            "id": "101",
            "id_line": "6"
        }
    },
    {
        "model": "metro.Station",
        "pk": 113,
        "fields": {
            "name_station": "Китай город КРЛ",
            "name_line": "6",
            "id": "102",
            "id_line": "6"
        }
    },
    {
        "model": "metro.Station",
        "pk": 114,
        "fields": {
            "name_station": "Третьяковская КРЛ",
            "name_line": "6",
            "id": "103",
            "id_line": "6"
        }
    },
    {
        "model": "metro.Station",
        "pk": 115,
        "fields": {
            "name_station": "Октябрьская КРЛ",
            "name_line": "6",
            "id": "104",
            "id_line": "6"
        }
    },
    {
        "model": "metro.Station",
        "pk": 116,
        "fields": {
            "name_station": "Шаболовская",
            "name_line": "6",
            "id": "105",
            "id_line": "6"
        }
    },
    {
        "model": "metro.Station",
        "pk": 117,
        "fields": {
            "name_station": "Ленинский проспект",
            "name_line": "6",
            "id": "106",
            "id_line": "6"
        }
    },
    {
        "model": "metro.Station",
        "pk": 118,
        "fields": {
            "name_station": "Академическая",
            "name_line": "6",
            "id": "107",
            "id_line": "6"
        }
    },
    {
        "model": "metro.Station",
        "pk": 119,
        "fields": {
            "name_station": "Профсоюзная",
            "name_line": "6",
            "id": "108",
            "id_line": "6"
        }
    },
    {
        "model": "metro.Station",
        "pk": 120,
        "fields": {
            "name_station": "Новые Черёмушки",
            "name_line": "6",
            "id": "109",
            "id_line": "6"
        }
    },
    {
        "model": "metro.Station",
        "pk": 121,
        "fields": {
            "name_station": "Калужская",
            "name_line": "6",
            "id": "110",
            "id_line": "6"
        }
    },
    {
        "model": "metro.Station",
        "pk": 122,
        "fields": {
            "name_station": "Беляево",
            "name_line": "6",
            "id": "111",
            "id_line": "6"
        }
    },
    {
        "model": "metro.Station",
        "pk": 123,
        "fields": {
            "name_station": "Коньково",
            "name_line": "6",
            "id": "112",
            "id_line": "6"
        }
    },
    {
        "model": "metro.Station",
        "pk": 124,
        "fields": {
            "name_station": "Тёплый стан",
            "name_line": "6",
            "id": "113",
            "id_line": "6"
        }
    },
    {
        "model": "metro.Station",
        "pk": 125,
        "fields": {
            "name_station": "Ясенево",
            "name_line": "6",
            "id": "114",
            "id_line": "6"
        }
    },
    {
        "model": "metro.Station",
        "pk": 126,
        "fields": {
            "name_station": "Новоясеневская",
            "name_line": "6",
            "id": "115",
            "id_line": "6"
        }
    },
    {
        "model": "metro.Station",
        "pk": 127,
        "fields": {
            "name_station": "Планерная",
            "name_line": "7",
            "id": "116",
            "id_line": "7"
        }
    },
    {
        "model": "metro.Station",
        "pk": 128,
        "fields": {
            "name_station": "Сходненская",
            "name_line": "7",
            "id": "117",
            "id_line": "7"
        }
    },
    {
        "model": "metro.Station",
        "pk": 129,
        "fields": {
            "name_station": "Тушинская",
            "name_line": "7",
            "id": "118",
            "id_line": "7"
        }
    },
    {
        "model": "metro.Station",
        "pk": 130,
        "fields": {
            "name_station": "Спартак",
            "name_line": "7",
            "id": "119",
            "id_line": "7"
        }
    },
    {
        "model": "metro.Station",
        "pk": 131,
        "fields": {
            "name_station": "Щукинская",
            "name_line": "7",
            "id": "120",
            "id_line": "7"
        }
    },
    {
        "model": "metro.Station",
        "pk": 132,
        "fields": {
            "name_station": "Октябрьское поле",
            "name_line": "7",
            "id": "121",
            "id_line": "7"
        }
    },
    {
        "model": "metro.Station",
        "pk": 133,
        "fields": {
            "name_station": "Полежаевская",
            "name_line": "7",
            "id": "122",
            "id_line": "7"
        }
    },
    {
        "model": "metro.Station",
        "pk": 134,
        "fields": {
            "name_station": "Беговая",
            "name_line": "7",
            "id": "123",
            "id_line": "7"
        }
    },
    {
        "model": "metro.Station",
        "pk": 135,
        "fields": {
            "name_station": "Улица 1905 года",
            "name_line": "7",
            "id": "124",
            "id_line": "7"
        }
    },
    {
        "model": "metro.Station",
        "pk": 136,
        "fields": {
            "name_station": "Баррикадная",
            "name_line": "7",
            "id": "125",
            "id_line": "7"
        }
    },
    {
        "model": "metro.Station",
        "pk": 137,
        "fields": {
            "name_station": "Пушкинская",
            "name_line": "7",
            "id": "126",
            "id_line": "7"
        }
    },
    {
        "model": "metro.Station",
        "pk": 138,
        "fields": {
            "name_station": "Кузнецкий мост",
            "name_line": "7",
            "id": "127",
            "id_line": "7"
        }
    },
    {
        "model": "metro.Station",
        "pk": 139,
        "fields": {
            "name_station": "Китай-город ТКЛ",
            "name_line": "7",
            "id": "128",
            "id_line": "7"
        }
    },
    {
        "model": "metro.Station",
        "pk": 140,
        "fields": {
            "name_station": "Таганская ТКЛ",
            "name_line": "7",
            "id": "129",
            "id_line": "7"
        }
    },
    {
        "model": "metro.Station",
        "pk": 141,
        "fields": {
            "name_station": "Пролетарская",
            "name_line": "7",
            "id": "130",
            "id_line": "7"
        }
    },
    {
        "model": "metro.Station",
        "pk": 142,
        "fields": {
            "name_station": "Волгоградский проспект",
            "name_line": "7",
            "id": "131",
            "id_line": "7"
        }
    },
    {
        "model": "metro.Station",
        "pk": 143,
        "fields": {
            "name_station": "Текстильщики",
            "name_line": "7",
            "id": "132",
            "id_line": "7"
        }
    },
    {
        "model": "metro.Station",
        "pk": 144,
        "fields": {
            "name_station": "Кузьминки",
            "name_line": "7",
            "id": "133",
            "id_line": "7"
        }
    },
    {
        "model": "metro.Station",
        "pk": 145,
        "fields": {
            "name_station": "Рязанский проспект",
            "name_line": "7",
            "id": "134",
            "id_line": "7"
        }
    },
    {
        "model": "metro.Station",
        "pk": 146,
        "fields": {
            "name_station": "Выхино",
            "name_line": "7",
            "id": "135",
            "id_line": "7"
        }
    },
    {
        "model": "metro.Station",
        "pk": 147,
        "fields": {
            "name_station": "Лермонтовский проспект",
            "name_line": "7",
            "id": "136",
            "id_line": "7"
        }
    },
    {
        "model": "metro.Station",
        "pk": 148,
        "fields": {
            "name_station": "Жулебино",
            "name_line": "7",
            "id": "137",
            "id_line": "7"
        }
    },
    {
        "model": "metro.Station",
        "pk": 149,
        "fields": {
            "name_station": "Котельники",
            "name_line": "7",
            "id": "138",
            "id_line": "7"
        }
    },
    {
        "model": "metro.Station",
        "pk": 150,
        "fields": {
            "name_station": "Третьяковская КЛ",
            "name_line": "8",
            "id": "146",
            "id_line": "8"
        }
    },
    {
        "model": "metro.Station",
        "pk": 151,
        "fields": {
            "name_station": "Марксистская",
            "name_line": "8",
            "id": "145",
            "id_line": "8"
        }
    },
    {
        "model": "metro.Station",
        "pk": 152,
        "fields": {
            "name_station": "Площадь Ильича",
            "name_line": "8",
            "id": "144",
            "id_line": "8"
        }
    },
    {
        "model": "metro.Station",
        "pk": 153,
        "fields": {
            "name_station": "Авиамоторная",
            "name_line": "8",
            "id": "143",
            "id_line": "8"
        }
    },
    {
        "model": "metro.Station",
        "pk": 154,
        "fields": {
            "name_station": "Шоссе Энтузиастов",
            "name_line": "8",
            "id": "142",
            "id_line": "8"
        }
    },
    {
        "model": "metro.Station",
        "pk": 155,
        "fields": {
            "name_station": "Перово",
            "name_line": "8",
            "id": "141",
            "id_line": "8"
        }
    },
    {
        "model": "metro.Station",
        "pk": 156,
        "fields": {
            "name_station": "Новогиреево",
            "name_line": "8",
            "id": "140",
            "id_line": "8"
        }
    },
    {
        "model": "metro.Station",
        "pk": 157,
        "fields": {
            "name_station": "Новокосино",
            "name_line": "8",
            "id": "139",
            "id_line": "8"
        }
    },
    {
        "model": "metro.Station",
        "pk": 158,
        "fields": {
            "name_station": "Деловой центр",
            "name_line": "8А",
            "id": "147",
            "id_line": "8"
        }
    },
    {
        "model": "metro.Station",
        "pk": 159,
        "fields": {
            "name_station": "Парк Победы СЛ",
            "name_line": "8А",
            "id": "148",
            "id_line": "8"
        }
    },
    {
        "model": "metro.Station",
        "pk": 160,
        "fields": {
            "name_station": "Минская",
            "name_line": "8А",
            "id": "241",
            "id_line": "8"
        }
    },
    {
        "model": "metro.Station",
        "pk": 161,
        "fields": {
            "name_station": "Ломоносовский проспект",
            "name_line": "8А",
            "id": "242",
            "id_line": "8"
        }
    },
    {
        "model": "metro.Station",
        "pk": 162,
        "fields": {
            "name_station": "Раменки",
            "name_line": "8А",
            "id": "243",
            "id_line": "8"
        }
    },
    {
        "model": "metro.Station",
        "pk": 163,
        "fields": {
            "name_station": "Мичуринский проспект",
            "name_line": "8А",
            "id": "253",
            "id_line": "8"
        }
    },
    {
        "model": "metro.Station",
        "pk": 164,
        "fields": {
            "name_station": "Озерная",
            "name_line": "8А",
            "id": "254",
            "id_line": "8"
        }
    },
    {
        "model": "metro.Station",
        "pk": 165,
        "fields": {
            "name_station": "Говорово",
            "name_line": "8А",
            "id": "255",
            "id_line": "8"
        }
    },
    {
        "model": "metro.Station",
        "pk": 166,
        "fields": {
            "name_station": "Солнцево",
            "name_line": "8А",
            "id": "256",
            "id_line": "8"
        }
    },
    {
        "model": "metro.Station",
        "pk": 167,
        "fields": {
            "name_station": "Боровское шоссе",
            "name_line": "8А",
            "id": "257",
            "id_line": "8"
        }
    },
    {
        "model": "metro.Station",
        "pk": 168,
        "fields": {
            "name_station": "Новопеределкино",
            "name_line": "8А",
            "id": "258",
            "id_line": "8"
        }
    },
    {
        "model": "metro.Station",
        "pk": 169,
        "fields": {
            "name_station": "Рассказовка",
            "name_line": "8А",
            "id": "259",
            "id_line": "8"
        }
    },
    {
        "model": "metro.Station",
        "pk": 170,
        "fields": {
            "name_station": "Пыхтино",
            "name_line": "8А",
            "id": "408",
            "id_line": "8"
        }
    },
    {
        "model": "metro.Station",
        "pk": 171,
        "fields": {
            "name_station": "Аэропорт Внуково",
            "name_line": "8А",
            "id": "409",
            "id_line": "8"
        }
    },
    {
        "model": "metro.Station",
        "pk": 172,
        "fields": {
            "name_station": "Алтуфьево",
            "name_line": "9",
            "id": "149",
            "id_line": "9"
        }
    },
    {
        "model": "metro.Station",
        "pk": 173,
        "fields": {
            "name_station": "Бибирево",
            "name_line": "9",
            "id": "150",
            "id_line": "9"
        }
    },
    {
        "model": "metro.Station",
        "pk": 174,
        "fields": {
            "name_station": "Отрадное",
            "name_line": "9",
            "id": "151",
            "id_line": "9"
        }
    },
    {
        "model": "metro.Station",
        "pk": 175,
        "fields": {
            "name_station": "Владыкино",
            "name_line": "9",
            "id": "152",
            "id_line": "9"
        }
    },
    {
        "model": "metro.Station",
        "pk": 176,
        "fields": {
            "name_station": "Петровско-Разумовская",
            "name_line": "9",
            "id": "153",
            "id_line": "9"
        }
    },
    {
        "model": "metro.Station",
        "pk": 177,
        "fields": {
            "name_station": "Тимирязевская",
            "name_line": "9",
            "id": "154",
            "id_line": "9"
        }
    },
    {
        "model": "metro.Station",
        "pk": 178,
        "fields": {
            "name_station": "Дмитровская",
            "name_line": "9",
            "id": "155",
            "id_line": "9"
        }
    },
    {
        "model": "metro.Station",
        "pk": 179,
        "fields": {
            "name_station": "Савеловская",
            "name_line": "9",
            "id": "156",
            "id_line": "9"
        }
    },
    {
        "model": "metro.Station",
        "pk": 180,
        "fields": {
            "name_station": "Менделеевская",
            "name_line": "9",
            "id": "157",
            "id_line": "9"
        }
    },
    {
        "model": "metro.Station",
        "pk": 181,
        "fields": {
            "name_station": "Цветной бульвар",
            "name_line": "9",
            "id": "158",
            "id_line": "9"
        }
    },
    {
        "model": "metro.Station",
        "pk": 182,
        "fields": {
            "name_station": "Чеховская",
            "name_line": "9",
            "id": "159",
            "id_line": "9"
        }
    },
    {
        "model": "metro.Station",
        "pk": 183,
        "fields": {
            "name_station": "Боровицкая",
            "name_line": "9",
            "id": "160",
            "id_line": "9"
        }
    },
    {
        "model": "metro.Station",
        "pk": 184,
        "fields": {
            "name_station": "Полянка",
            "name_line": "9",
            "id": "161",
            "id_line": "9"
        }
    },
    {
        "model": "metro.Station",
        "pk": 185,
        "fields": {
            "name_station": "Серпуховская",
            "name_line": "9",
            "id": "162",
            "id_line": "9"
        }
    },
    {
        "model": "metro.Station",
        "pk": 186,
        "fields": {
            "name_station": "Тульская",
            "name_line": "9",
            "id": "163",
            "id_line": "9"
        }
    },
    {
        "model": "metro.Station",
        "pk": 187,
        "fields": {
            "name_station": "Нагатинская",
            "name_line": "9",
            "id": "164",
            "id_line": "9"
        }
    },
    {
        "model": "metro.Station",
        "pk": 188,
        "fields": {
            "name_station": "Нагорная",
            "name_line": "9",
            "id": "165",
            "id_line": "9"
        }
    },
    {
        "model": "metro.Station",
        "pk": 189,
        "fields": {
            "name_station": "Нахимовский проспект",
            "name_line": "9",
            "id": "166",
            "id_line": "9"
        }
    },
    {
        "model": "metro.Station",
        "pk": 190,
        "fields": {
            "name_station": "Севастопольская",
            "name_line": "9",
            "id": "167",
            "id_line": "9"
        }
    },
    {
        "model": "metro.Station",
        "pk": 191,
        "fields": {
            "name_station": "Чертановская",
            "name_line": "9",
            "id": "168",
            "id_line": "9"
        }
    },
    {
        "model": "metro.Station",
        "pk": 192,
        "fields": {
            "name_station": "Южная",
            "name_line": "9",
            "id": "169",
            "id_line": "9"
        }
    },
    {
        "model": "metro.Station",
        "pk": 193,
        "fields": {
            "name_station": "Пражская",
            "name_line": "9",
            "id": "170",
            "id_line": "9"
        }
    },
    {
        "model": "metro.Station",
        "pk": 194,
        "fields": {
            "name_station": "Улица Академика Янгеля",
            "name_line": "9",
            "id": "171",
            "id_line": "9"
        }
    },
    {
        "model": "metro.Station",
        "pk": 195,
        "fields": {
            "name_station": "Аннино",
            "name_line": "9",
            "id": "172",
            "id_line": "9"
        }
    },
    {
        "model": "metro.Station",
        "pk": 196,
        "fields": {
            "name_station": "Бульвар Дмитрия Донского",
            "name_line": "9",
            "id": "173",
            "id_line": "9"
        }
    },
    {
        "model": "metro.Station",
        "pk": 197,
        "fields": {
            "name_station": "Физтех",
            "name_line": "10",
            "id": "412",
            "id_line": "10"
        }
    },
    {
        "model": "metro.Station",
        "pk": 198,
        "fields": {
            "name_station": "Лианозово",
            "name_line": "10",
            "id": "411",
            "id_line": "10"
        }
    },
    {
        "model": "metro.Station",
        "pk": 199,
        "fields": {
            "name_station": "Яхромская",
            "name_line": "10",
            "id": "410",
            "id_line": "10"
        }
    },
    {
        "model": "metro.Station",
        "pk": 200,
        "fields": {
            "name_station": "Селигерская",
            "name_line": "10",
            "id": "250",
            "id_line": "10"
        }
    },
    {
        "model": "metro.Station",
        "pk": 201,
        "fields": {
            "name_station": "Верхние Лихоборы",
            "name_line": "10",
            "id": "251",
            "id_line": "10"
        }
    },
    {
        "model": "metro.Station",
        "pk": 202,
        "fields": {
            "name_station": "Окружная",
            "name_line": "10",
            "id": "252",
            "id_line": "10"
        }
    },
    {
        "model": "metro.Station",
        "pk": 203,
        "fields": {
            "name_station": "Петровско-Разумовская ЛДЛ",
            "name_line": "10",
            "id": "234",
            "id_line": "10"
        }
    },
    {
        "model": "metro.Station",
        "pk": 204,
        "fields": {
            "name_station": "Фонвизинская",
            "name_line": "10",
            "id": "233",
            "id_line": "10"
        }
    },
    {
        "model": "metro.Station",
        "pk": 205,
        "fields": {
            "name_station": "Бутырская",
            "name_line": "10",
            "id": "232",
            "id_line": "10"
        }
    },
    {
        "model": "metro.Station",
        "pk": 206,
        "fields": {
            "name_station": "Марьина Роща",
            "name_line": "10",
            "id": "174",
            "id_line": "10"
        }
    },
    {
        "model": "metro.Station",
        "pk": 207,
        "fields": {
            "name_station": "Достоевская",
            "name_line": "10",
            "id": "175",
            "id_line": "10"
        }
    },
    {
        "model": "metro.Station",
        "pk": 208,
        "fields": {
            "name_station": "Трубная",
            "name_line": "10",
            "id": "176",
            "id_line": "10"
        }
    },
    {
        "model": "metro.Station",
        "pk": 209,
        "fields": {
            "name_station": "Сретенский бульвар",
            "name_line": "10",
            "id": "177",
            "id_line": "10"
        }
    },
    {
        "model": "metro.Station",
        "pk": 210,
        "fields": {
            "name_station": "Чкаловская",
            "name_line": "10",
            "id": "178",
            "id_line": "10"
        }
    },
    {
        "model": "metro.Station",
        "pk": 211,
        "fields": {
            "name_station": "Римская",
            "name_line": "10",
            "id": "179",
            "id_line": "10"
        }
    },
    {
        "model": "metro.Station",
        "pk": 212,
        "fields": {
            "name_station": "Крестьянская застава",
            "name_line": "10",
            "id": "180",
            "id_line": "10"
        }
    },
    {
        "model": "metro.Station",
        "pk": 213,
        "fields": {
            "name_station": "Дубровка",
            "name_line": "10",
            "id": "181",
            "id_line": "10"
        }
    },
    {
        "model": "metro.Station",
        "pk": 214,
        "fields": {
            "name_station": "Кожуховская",
            "name_line": "10",
            "id": "182",
            "id_line": "10"
        }
    },
    {
        "model": "metro.Station",
        "pk": 215,
        "fields": {
            "name_station": "Печатники",
            "name_line": "10",
            "id": "183",
            "id_line": "10"
        }
    },
    {
        "model": "metro.Station",
        "pk": 216,
        "fields": {
            "name_station": "Волжская",
            "name_line": "10",
            "id": "184",
            "id_line": "10"
        }
    },
    {
        "model": "metro.Station",
        "pk": 217,
        "fields": {
            "name_station": "Люблино",
            "name_line": "10",
            "id": "185",
            "id_line": "10"
        }
    },
    {
        "model": "metro.Station",
        "pk": 218,
        "fields": {
            "name_station": "Братиславская",
            "name_line": "10",
            "id": "186",
            "id_line": "10"
        }
    },
    {
        "model": "metro.Station",
        "pk": 219,
        "fields": {
            "name_station": "Марьино",
            "name_line": "10",
            "id": "187",
            "id_line": "10"
        }
    },
    {
        "model": "metro.Station",
        "pk": 220,
        "fields": {
            "name_station": "Борисово",
            "name_line": "10",
            "id": "188",
            "id_line": "10"
        }
    },
    {
        "model": "metro.Station",
        "pk": 221,
        "fields": {
            "name_station": "Шипиловская",
            "name_line": "10",
            "id": "189",
            "id_line": "10"
        }
    },
    {
        "model": "metro.Station",
        "pk": 222,
        "fields": {
            "name_station": "Зябликово",
            "name_line": "10",
            "id": "190",
            "id_line": "10"
        }
    },
    {
        "model": "metro.Station",
        "pk": 223,
        "fields": {
            "name_station": "Битцевский парк",
            "name_line": "Л1",
            "id": "194",
            "id_line": "12"
        }
    },
    {
        "model": "metro.Station",
        "pk": 224,
        "fields": {
            "name_station": "Лесопарковая",
            "name_line": "Л1",
            "id": "195",
            "id_line": "12"
        }
    },
    {
        "model": "metro.Station",
        "pk": 225,
        "fields": {
            "name_station": "Улица Старокачаловская",
            "name_line": "Л1",
            "id": "196",
            "id_line": "12"
        }
    },
    {
        "model": "metro.Station",
        "pk": 226,
        "fields": {
            "name_station": "Улица Скобелевская",
            "name_line": "Л1",
            "id": "197",
            "id_line": "12"
        }
    },
    {
        "model": "metro.Station",
        "pk": 227,
        "fields": {
            "name_station": "Бульвар Адмирала Ушакова",
            "name_line": "Л1",
            "id": "198",
            "id_line": "12"
        }
    },
    {
        "model": "metro.Station",
        "pk": 228,
        "fields": {
            "name_station": "Улица Горчакова",
            "name_line": "Л1",
            "id": "199",
            "id_line": "12"
        }
    },
    {
        "model": "metro.Station",
        "pk": 229,
        "fields": {
            "name_station": "Бунинская аллея",
            "name_line": "Л1",
            "id": "200",
            "id_line": "12"
        }
    },
    {
        "model": "metro.Station",
        "pk": 230,
        "fields": {
            "name_station": "МЦК Ростокино",
            "name_line": "14",
            "id": "204",
            "id_line": "14"
        }
    },
    {
        "model": "metro.Station",
        "pk": 231,
        "fields": {
            "name_station": "МЦК Белокаменная",
            "name_line": "14",
            "id": "205",
            "id_line": "14"
        }
    },
    {
        "model": "metro.Station",
        "pk": 232,
        "fields": {
            "name_station": "МЦК Бульвар Рокоссовского",
            "name_line": "14",
            "id": "206",
            "id_line": "14"
        }
    },
    {
        "model": "metro.Station",
        "pk": 233,
        "fields": {
            "name_station": "МЦК Локомотив",
            "name_line": "14",
            "id": "207",
            "id_line": "14"
        }
    },
    {
        "model": "metro.Station",
        "pk": 234,
        "fields": {
            "name_station": "МЦК Измайлово",
            "name_line": "14",
            "id": "208",
            "id_line": "14"
        }
    },
    {
        "model": "metro.Station",
        "pk": 235,
        "fields": {
            "name_station": "МЦК Соколиная Гора",
            "name_line": "14",
            "id": "209",
            "id_line": "14"
        }
    },
    {
        "model": "metro.Station",
        "pk": 236,
        "fields": {
            "name_station": "МЦК Шоссе Энтузиастов",
            "name_line": "14",
            "id": "210",
            "id_line": "14"
        }
    },
    {
        "model": "metro.Station",
        "pk": 237,
        "fields": {
            "name_station": "МЦК Андроновка",
            "name_line": "14",
            "id": "211",
            "id_line": "14"
        }
    },
    {
        "model": "metro.Station",
        "pk": 238,
        "fields": {
            "name_station": "МЦК Нижегородская",
            "name_line": "14",
            "id": "212",
            "id_line": "14"
        }
    },
    {
        "model": "metro.Station",
        "pk": 239,
        "fields": {
            "name_station": "МЦК Новохохловская",
            "name_line": "14",
            "id": "213",
            "id_line": "14"
        }
    },
    {
        "model": "metro.Station",
        "pk": 240,
        "fields": {
            "name_station": "МЦК Угрешская",
            "name_line": "14",
            "id": "214",
            "id_line": "14"
        }
    },
    {
        "model": "metro.Station",
        "pk": 241,
        "fields": {
            "name_station": "МЦК Дубровка",
            "name_line": "14",
            "id": "215",
            "id_line": "14"
        }
    },
    {
        "model": "metro.Station",
        "pk": 242,
        "fields": {
            "name_station": "МЦК Автозаводская",
            "name_line": "14",
            "id": "216",
            "id_line": "14"
        }
    },
    {
        "model": "metro.Station",
        "pk": 243,
        "fields": {
            "name_station": "МЦК ЗИЛ",
            "name_line": "14",
            "id": "217",
            "id_line": "14"
        }
    },
    {
        "model": "metro.Station",
        "pk": 244,
        "fields": {
            "name_station": "МЦК Верхние Котлы",
            "name_line": "14",
            "id": "218",
            "id_line": "14"
        }
    },
    {
        "model": "metro.Station",
        "pk": 245,
        "fields": {
            "name_station": "МЦК Крымская",
            "name_line": "14",
            "id": "219",
            "id_line": "14"
        }
    },
    {
        "model": "metro.Station",
        "pk": 246,
        "fields": {
            "name_station": "МЦК Площадь Гагарина",
            "name_line": "14",
            "id": "220",
            "id_line": "14"
        }
    },
    {
        "model": "metro.Station",
        "pk": 247,
        "fields": {
            "name_station": "МЦК Лужники",
            "name_line": "14",
            "id": "221",
            "id_line": "14"
        }
    },
    {
        "model": "metro.Station",
        "pk": 248,
        "fields": {
            "name_station": "МЦК Кутузовская",
            "name_line": "14",
            "id": "222",
            "id_line": "14"
        }
    },
    {
        "model": "metro.Station",
        "pk": 249,
        "fields": {
            "name_station": "МЦК Москва-Сити",
            "name_line": "14",
            "id": "452",
            "id_line": "14"
        }
    },
    {
        "model": "metro.Station",
        "pk": 250,
        "fields": {
            "name_station": "МЦК Шелепиха",
            "name_line": "14",
            "id": "224",
            "id_line": "14"
        }
    },
    {
        "model": "metro.Station",
        "pk": 251,
        "fields": {
            "name_station": "МЦК Хорошёво",
            "name_line": "14",
            "id": "225",
            "id_line": "14"
        }
    },
    {
        "model": "metro.Station",
        "pk": 252,
        "fields": {
            "name_station": "МЦК Зорге",
            "name_line": "14",
            "id": "226",
            "id_line": "14"
        }
    },
    {
        "model": "metro.Station",
        "pk": 253,
        "fields": {
            "name_station": "МЦК Панфиловская",
            "name_line": "14",
            "id": "227",
            "id_line": "14"
        }
    },
    {
        "model": "metro.Station",
        "pk": 254,
        "fields": {
            "name_station": "МЦК Стрешнево",
            "name_line": "14",
            "id": "228",
            "id_line": "14"
        }
    },
    {
        "model": "metro.Station",
        "pk": 255,
        "fields": {
            "name_station": "МЦК Балтийская",
            "name_line": "14",
            "id": "229",
            "id_line": "14"
        }
    },
    {
        "model": "metro.Station",
        "pk": 256,
        "fields": {
            "name_station": "МЦК Коптево",
            "name_line": "14",
            "id": "230",
            "id_line": "14"
        }
    },
    {
        "model": "metro.Station",
        "pk": 257,
        "fields": {
            "name_station": "МЦК Лихоборы",
            "name_line": "14",
            "id": "231",
            "id_line": "14"
        }
    },
    {
        "model": "metro.Station",
        "pk": 258,
        "fields": {
            "name_station": "МЦК Окружная",
            "name_line": "14",
            "id": "201",
            "id_line": "14"
        }
    },
    {
        "model": "metro.Station",
        "pk": 259,
        "fields": {
            "name_station": "МЦК Владыкино",
            "name_line": "14",
            "id": "202",
            "id_line": "14"
        }
    },
    {
        "model": "metro.Station",
        "pk": 260,
        "fields": {
            "name_station": "МЦК Ботанический сад",
            "name_line": "14",
            "id": "203",
            "id_line": "14"
        }
    },
    {
        "model": "metro.Station",
        "pk": 261,
        "fields": {
            "name_station": "МЦК Ростокино",
            "name_line": "14",
            "id": "204",
            "id_line": "14"
        }
    },
    {
        "model": "metro.Station",
        "pk": 262,
        "fields": {
            "name_station": "БКЛ Савеловская",
            "name_line": "БКЛ",
            "id": "261",
            "id_line": "11"
        }
    },
    {
        "model": "metro.Station",
        "pk": 263,
        "fields": {
            "name_station": "БКЛ Петровский Парк",
            "name_line": "БКЛ",
            "id": "249",
            "id_line": "11"
        }
    },
    {
        "model": "metro.Station",
        "pk": 264,
        "fields": {
            "name_station": "БКЛ ЦСКА",
            "name_line": "БКЛ",
            "id": "248",
            "id_line": "11"
        }
    },
    {
        "model": "metro.Station",
        "pk": 265,
        "fields": {
            "name_station": "БКЛ Хорошёвская",
            "name_line": "БКЛ",
            "id": "247",
            "id_line": "11"
        }
    },
    {
        "model": "metro.Station",
        "pk": 266,
        "fields": {
            "name_station": "БКЛ Народное Ополчение",
            "name_line": "БКЛ",
            "id": "341",
            "id_line": "11"
        }
    },
    {
        "model": "metro.Station",
        "pk": 267,
        "fields": {
            "name_station": "БКЛ Мнёвники",
            "name_line": "БКЛ",
            "id": "342",
            "id_line": "11"
        }
    },
    {
        "model": "metro.Station",
        "pk": 268,
        "fields": {
            "name_station": "БКЛ Терехово",
            "name_line": "БКЛ",
            "id": "343",
            "id_line": "11"
        }
    },
    {
        "model": "metro.Station",
        "pk": 269,
        "fields": {
            "name_station": "БКЛ Кунцевская",
            "name_line": "БКЛ",
            "id": "344",
            "id_line": "11"
        }
    },
    {
        "model": "metro.Station",
        "pk": 270,
        "fields": {
            "name_station": "БКЛ Давыдково",
            "name_line": "БКЛ",
            "id": "345",
            "id_line": "11"
        }
    },
    {
        "model": "metro.Station",
        "pk": 271,
        "fields": {
            "name_station": "БКЛ Аминьевская",
            "name_line": "БКЛ",
            "id": "346",
            "id_line": "11"
        }
    },
    {
        "model": "metro.Station",
        "pk": 272,
        "fields": {
            "name_station": "БКЛ Мичуринский проспект",
            "name_line": "БКЛ",
            "id": "347",
            "id_line": "11"
        }
    },
    {
        "model": "metro.Station",
        "pk": 273,
        "fields": {
            "name_station": "БКЛ Проспект Вернадского",
            "name_line": "БКЛ",
            "id": "348",
            "id_line": "11"
        }
    },
    {
        "model": "metro.Station",
        "pk": 274,
        "fields": {
            "name_station": "БКЛ Новаторская",
            "name_line": "БКЛ",
            "id": "349",
            "id_line": "11"
        }
    },
    {
        "model": "metro.Station",
        "pk": 275,
        "fields": {
            "name_station": "БКЛ Воронцовская",
            "name_line": "БКЛ",
            "id": "350",
            "id_line": "11"
        }
    },
    {
        "model": "metro.Station",
        "pk": 276,
        "fields": {
            "name_station": "БКЛ Зюзино",
            "name_line": "БКЛ",
            "id": "351",
            "id_line": "11"
        }
    },
    {
        "model": "metro.Station",
        "pk": 277,
        "fields": {
            "name_station": "БКЛ Каховская",
            "name_line": "БКЛ",
            "id": "191",
            "id_line": "11"
        }
    },
    {
        "model": "metro.Station",
        "pk": 278,
        "fields": {
            "name_station": "БКЛ Варшавская",
            "name_line": "БКЛ",
            "id": "364",
            "id_line": "11"
        }
    },
    {
        "model": "metro.Station",
        "pk": 279,
        "fields": {
            "name_station": "БКЛ Каширская",
            "name_line": "БКЛ",
            "id": "365",
            "id_line": "11"
        }
    },
    {
        "model": "metro.Station",
        "pk": 280,
        "fields": {
            "name_station": "БКЛ Кленовый бульвар",
            "name_line": "БКЛ",
            "id": "353",
            "id_line": "11"
        }
    },
    {
        "model": "metro.Station",
        "pk": 281,
        "fields": {
            "name_station": "БКЛ Нагатинский Затон",
            "name_line": "БКЛ",
            "id": "354",
            "id_line": "11"
        }
    },
    {
        "model": "metro.Station",
        "pk": 282,
        "fields": {
            "name_station": "БКЛ Печатники",
            "name_line": "БКЛ",
            "id": "355",
            "id_line": "11"
        }
    },
    {
        "model": "metro.Station",
        "pk": 283,
        "fields": {
            "name_station": "БКЛ Текстильщики",
            "name_line": "БКЛ",
            "id": "356",
            "id_line": "11"
        }
    },
    {
        "model": "metro.Station",
        "pk": 284,
        "fields": {
            "name_station": "БКЛ Нижегородская",
            "name_line": "БКЛ",
            "id": "357",
            "id_line": "11"
        }
    },
    {
        "model": "metro.Station",
        "pk": 285,
        "fields": {
            "name_station": "БКЛ Авиамоторная",
            "name_line": "БКЛ",
            "id": "358",
            "id_line": "11"
        }
    },
    {
        "model": "metro.Station",
        "pk": 286,
        "fields": {
            "name_station": "БКЛ Лефортово",
            "name_line": "БКЛ",
            "id": "359",
            "id_line": "11"
        }
    },
    {
        "model": "metro.Station",
        "pk": 287,
        "fields": {
            "name_station": "БКЛ Электрозаводская",
            "name_line": "БКЛ",
            "id": "360",
            "id_line": "11"
        }
    },
    {
        "model": "metro.Station",
        "pk": 288,
        "fields": {
            "name_station": "БКЛ Сокольники",
            "name_line": "БКЛ",
            "id": "361",
            "id_line": "11"
        }
    },
    {
        "model": "metro.Station",
        "pk": 289,
        "fields": {
            "name_station": "БКЛ Рижская",
            "name_line": "БКЛ",
            "id": "362",
            "id_line": "11"
        }
    },
    {
        "model": "metro.Station",
        "pk": 290,
        "fields": {
            "name_station": "БКЛ Марьина Роща",
            "name_line": "БКЛ",
            "id": "363",
            "id_line": "11"
        }
    },
    {
        "model": "metro.Station",
        "pk": 291,
        "fields": {
            "name_station": "БКЛ Савеловская",
            "name_line": "БКЛ",
            "id": "261",
            "id_line": "11"
        }
    },
    {
        "model": "metro.Station",
        "pk": 292,
        "fields": {
            "name_station": "БКЛ Савеловская",
            "name_line": "БКЛ(А)",
            "id": "261",
            "id_line": "11"
        }
    },
    {
        "model": "metro.Station",
        "pk": 293,
        "fields": {
            "name_station": "БКЛ Петровский Парк",
            "name_line": "БКЛ(А)",
            "id": "249",
            "id_line": "11"
        }
    },
    {
        "model": "metro.Station",
        "pk": 294,
        "fields": {
            "name_station": "БКЛ ЦСКА",
            "name_line": "БКЛ(А)",
            "id": "248",
            "id_line": "11"
        }
    },
    {
        "model": "metro.Station",
        "pk": 295,
        "fields": {
            "name_station": "БКЛ Хорошёвская",
            "name_line": "БКЛ(А)",
            "id": "247",
            "id_line": "11"
        }
    },
    {
        "model": "metro.Station",
        "pk": 296,
        "fields": {
            "name_station": "БКЛ Шелепиха",
            "name_line": "БКЛ(А)",
            "id": "246",
            "id_line": "11"
        }
    },
    {
        "model": "metro.Station",
        "pk": 297,
        "fields": {
            "name_station": "БКЛ Деловой центр",
            "name_line": "БКЛ(А)",
            "id": "245",
            "id_line": "11"
        }
    },
    {
        "model": "metro.Station",
        "pk": 298,
        "fields": {
            "name_station": "Нижегородская",
            "name_line": "15",
            "id": "335",
            "id_line": "15"
        }
    },
    {
        "model": "metro.Station",
        "pk": 299,
        "fields": {
            "name_station": "Стахановская",
            "name_line": "15",
            "id": "334",
            "id_line": "15"
        }
    },
    {
        "model": "metro.Station",
        "pk": 300,
        "fields": {
            "name_station": "Окская",
            "name_line": "15",
            "id": "333",
            "id_line": "15"
        }
    },
    {
        "model": "metro.Station",
        "pk": 301,
        "fields": {
            "name_station": "Юго-Восточная",
            "name_line": "15",
            "id": "332",
            "id_line": "15"
        }
    },
    {
        "model": "metro.Station",
        "pk": 302,
        "fields": {
            "name_station": "Косино",
            "name_line": "15",
            "id": "265",
            "id_line": "15"
        }
    },
    {
        "model": "metro.Station",
        "pk": 303,
        "fields": {
            "name_station": "Улица Дмитриевского",
            "name_line": "15",
            "id": "264",
            "id_line": "15"
        }
    },
    {
        "model": "metro.Station",
        "pk": 304,
        "fields": {
            "name_station": "Лухмановская",
            "name_line": "15",
            "id": "263",
            "id_line": "15"
        }
    },
    {
        "model": "metro.Station",
        "pk": 305,
        "fields": {
            "name_station": "Некрасовка",
            "name_line": "15",
            "id": "262",
            "id_line": "15"
        }
    },
    {
        "model": "metro.Station",
        "pk": 306,
        "fields": {
            "name_station": "Лобня МЦД-1(П)",
            "name_line": "Д1",
            "id": "270",
            "id_line": "16"
        }
    },
    {
        "model": "metro.Station",
        "pk": 307,
        "fields": {
            "name_station": "Шереметьевская МЦД-1(П)",
            "name_line": "Д1",
            "id": "271",
            "id_line": "16"
        }
    },
    {
        "model": "metro.Station",
        "pk": 308,
        "fields": {
            "name_station": "Хлебниково МЦД-1(П)",
            "name_line": "Д1",
            "id": "272",
            "id_line": "16"
        }
    },
    {
        "model": "metro.Station",
        "pk": 309,
        "fields": {
            "name_station": "Водники МЦД-1(П)",
            "name_line": "Д1",
            "id": "273",
            "id_line": "16"
        }
    },
    {
        "model": "metro.Station",
        "pk": 310,
        "fields": {
            "name_station": "Долгопрудная МЦД-1(П)",
            "name_line": "Д1",
            "id": "274",
            "id_line": "16"
        }
    },
    {
        "model": "metro.Station",
        "pk": 311,
        "fields": {
            "name_station": "Новодачная МЦД-1(П)",
            "name_line": "Д1",
            "id": "275",
            "id_line": "16"
        }
    },
    {
        "model": "metro.Station",
        "pk": 312,
        "fields": {
            "name_station": "Марк МЦД-1",
            "name_line": "Д1",
            "id": "276",
            "id_line": "16"
        }
    },
    {
        "model": "metro.Station",
        "pk": 313,
        "fields": {
            "name_station": "Лианозово МЦД-1",
            "name_line": "Д1",
            "id": "277",
            "id_line": "16"
        }
    },
    {
        "model": "metro.Station",
        "pk": 314,
        "fields": {
            "name_station": "Бескудниково МЦД-1",
            "name_line": "Д1",
            "id": "278",
            "id_line": "16"
        }
    },
    {
        "model": "metro.Station",
        "pk": 315,
        "fields": {
            "name_station": "Дегунино МЦД-1",
            "name_line": "Д1",
            "id": "279",
            "id_line": "16"
        }
    },
    {
        "model": "metro.Station",
        "pk": 316,
        "fields": {
            "name_station": "Окружная МЦД-1",
            "name_line": "Д1",
            "id": "280",
            "id_line": "16"
        }
    },
    {
        "model": "metro.Station",
        "pk": 317,
        "fields": {
            "name_station": "Тимирязевская МЦД-1",
            "name_line": "Д1",
            "id": "282",
            "id_line": "16"
        }
    },
    {
        "model": "metro.Station",
        "pk": 318,
        "fields": {
            "name_station": "Савёловский вокзал МЦД-1",
            "name_line": "Д1",
            "id": "284",
            "id_line": "16"
        }
    },
    {
        "model": "metro.Station",
        "pk": 319,
        "fields": {
            "name_station": "Белорусский вокзал МЦД-1",
            "name_line": "Д1",
            "id": "285",
            "id_line": "16"
        }
    },
    {
        "model": "metro.Station",
        "pk": 320,
        "fields": {
            "name_station": "Беговая МЦД-1",
            "name_line": "Д1",
            "id": "286",
            "id_line": "16"
        }
    },
    {
        "model": "metro.Station",
        "pk": 321,
        "fields": {
            "name_station": "Тестовская МЦД-1",
            "name_line": "Д1",
            "id": "287",
            "id_line": "16"
        }
    },
    {
        "model": "metro.Station",
        "pk": 322,
        "fields": {
            "name_station": "Фили МЦД-1",
            "name_line": "Д1",
            "id": "288",
            "id_line": "16"
        }
    },
    {
        "model": "metro.Station",
        "pk": 323,
        "fields": {
            "name_station": "Славянский бульвар МЦД-1",
            "name_line": "Д1",
            "id": "289",
            "id_line": "16"
        }
    },
    {
        "model": "metro.Station",
        "pk": 324,
        "fields": {
            "name_station": "Кунцевская МЦД-1",
            "name_line": "Д1",
            "id": "290",
            "id_line": "16"
        }
    },
    {
        "model": "metro.Station",
        "pk": 325,
        "fields": {
            "name_station": "Рабочий Посёлок МЦД-1",
            "name_line": "Д1",
            "id": "291",
            "id_line": "16"
        }
    },
    {
        "model": "metro.Station",
        "pk": 326,
        "fields": {
            "name_station": "Сетунь МЦД-1",
            "name_line": "Д1",
            "id": "292",
            "id_line": "16"
        }
    },
    {
        "model": "metro.Station",
        "pk": 327,
        "fields": {
            "name_station": "Немчиновка МЦД-1(П)",
            "name_line": "Д1",
            "id": "293",
            "id_line": "16"
        }
    },
    {
        "model": "metro.Station",
        "pk": 328,
        "fields": {
            "name_station": "Сколково МЦД-1(П)",
            "name_line": "Д1",
            "id": "294",
            "id_line": "16"
        }
    },
    {
        "model": "metro.Station",
        "pk": 329,
        "fields": {
            "name_station": "Баковка МЦД-1(П)",
            "name_line": "Д1",
            "id": "295",
            "id_line": "16"
        }
    },
    {
        "model": "metro.Station",
        "pk": 330,
        "fields": {
            "name_station": "Одинцово МЦД-1(П)",
            "name_line": "Д1",
            "id": "296",
            "id_line": "16"
        }
    },
    {
        "model": "metro.Station",
        "pk": 331,
        "fields": {
            "name_station": "Нахабино МЦД-2(П)",
            "name_line": "Д2",
            "id": "297",
            "id_line": "17"
        }
    },
    {
        "model": "metro.Station",
        "pk": 332,
        "fields": {
            "name_station": "Аникеевка МЦД-2(П)",
            "name_line": "Д2",
            "id": "298",
            "id_line": "17"
        }
    },
    {
        "model": "metro.Station",
        "pk": 333,
        "fields": {
            "name_station": "Опалиха МЦД-2(П)",
            "name_line": "Д2",
            "id": "299",
            "id_line": "17"
        }
    },
    {
        "model": "metro.Station",
        "pk": 334,
        "fields": {
            "name_station": "Красногорская МЦД-2(П)",
            "name_line": "Д2",
            "id": "300",
            "id_line": "17"
        }
    },
    {
        "model": "metro.Station",
        "pk": 335,
        "fields": {
            "name_station": "Павшино МЦД-2(П)",
            "name_line": "Д2",
            "id": "301",
            "id_line": "17"
        }
    },
    {
        "model": "metro.Station",
        "pk": 336,
        "fields": {
            "name_station": "Пенягино МЦД-2(П)",
            "name_line": "Д2",
            "id": "302",
            "id_line": "17"
        }
    },
    {
        "model": "metro.Station",
        "pk": 337,
        "fields": {
            "name_station": "Волоколамская МЦД-2",
            "name_line": "Д2",
            "id": "331",
            "id_line": "17"
        }
    },
    {
        "model": "metro.Station",
        "pk": 338,
        "fields": {
            "name_station": "Трикотажная МЦД-2",
            "name_line": "Д2",
            "id": "303",
            "id_line": "17"
        }
    },
    {
        "model": "metro.Station",
        "pk": 339,
        "fields": {
            "name_station": "Тушинская МЦД-2",
            "name_line": "Д2",
            "id": "304",
            "id_line": "17"
        }
    },
    {
        "model": "metro.Station",
        "pk": 340,
        "fields": {
            "name_station": "Щукинская МЦД-2",
            "name_line": "Д2",
            "id": "305",
            "id_line": "17"
        }
    },
    {
        "model": "metro.Station",
        "pk": 341,
        "fields": {
            "name_station": "Стрешнево МЦД-2",
            "name_line": "Д2",
            "id": "306",
            "id_line": "17"
        }
    },
    {
        "model": "metro.Station",
        "pk": 342,
        "fields": {
            "name_station": "Красный Балтиец МЦД-2",
            "name_line": "Д2",
            "id": "307",
            "id_line": "17"
        }
    },
    {
        "model": "metro.Station",
        "pk": 343,
        "fields": {
            "name_station": "Гражданская МЦД-2",
            "name_line": "Д2",
            "id": "308",
            "id_line": "17"
        }
    },
    {
        "model": "metro.Station",
        "pk": 344,
        "fields": {
            "name_station": "Дмитровская МЦД-2",
            "name_line": "Д2",
            "id": "309",
            "id_line": "17"
        }
    },
    {
        "model": "metro.Station",
        "pk": 345,
        "fields": {
            "name_station": "Марьина Роща МЦД-2",
            "name_line": "Д2",
            "id": "366",
            "id_line": "17"
        }
    },
    {
        "model": "metro.Station",
        "pk": 346,
        "fields": {
            "name_station": "Рижская МЦД-2",
            "name_line": "Д2",
            "id": "310",
            "id_line": "17"
        }
    },
    {
        "model": "metro.Station",
        "pk": 347,
        "fields": {
            "name_station": "Площадь трёх вокзалов МЦД-2",
            "name_line": "Д2",
            "id": "311",
            "id_line": "17"
        }
    },
    {
        "model": "metro.Station",
        "pk": 348,
        "fields": {
            "name_station": "Курская МЦД-2",
            "name_line": "Д2",
            "id": "312",
            "id_line": "17"
        }
    },
    {
        "model": "metro.Station",
        "pk": 349,
        "fields": {
            "name_station": "Москва-Товарная МЦД-2",
            "name_line": "Д2",
            "id": "313",
            "id_line": "17"
        }
    },
    {
        "model": "metro.Station",
        "pk": 350,
        "fields": {
            "name_station": "Калитники МЦД-2",
            "name_line": "Д2",
            "id": "314",
            "id_line": "17"
        }
    },
    {
        "model": "metro.Station",
        "pk": 351,
        "fields": {
            "name_station": "Новохохловская МЦД-2",
            "name_line": "Д2",
            "id": "315",
            "id_line": "17"
        }
    },
    {
        "model": "metro.Station",
        "pk": 352,
        "fields": {
            "name_station": "Текстильщики МЦД-2",
            "name_line": "Д2",
            "id": "316",
            "id_line": "17"
        }
    },
    {
        "model": "metro.Station",
        "pk": 353,
        "fields": {
            "name_station": "Печатники МЦД-2",
            "name_line": "Д2",
            "id": "352",
            "id_line": "17"
        }
    },
    {
        "model": "metro.Station",
        "pk": 354,
        "fields": {
            "name_station": "Кубанская МЦД-2",
            "name_line": "Д2",
            "id": "318",
            "id_line": "17"
        }
    },
    {
        "model": "metro.Station",
        "pk": 355,
        "fields": {
            "name_station": "Депо МЦД-2",
            "name_line": "Д2",
            "id": "319",
            "id_line": "17"
        }
    },
    {
        "model": "metro.Station",
        "pk": 356,
        "fields": {
            "name_station": "Перерва МЦД-2",
            "name_line": "Д2",
            "id": "320",
            "id_line": "17"
        }
    },
    {
        "model": "metro.Station",
        "pk": 357,
        "fields": {
            "name_station": "Курьяново",
            "name_line": "Д2",
            "id": "339",
            "id_line": "17"
        }
    },
    {
        "model": "metro.Station",
        "pk": 358,
        "fields": {
            "name_station": "Москворечье МЦД-2",
            "name_line": "Д2",
            "id": "321",
            "id_line": "17"
        }
    },
    {
        "model": "metro.Station",
        "pk": 359,
        "fields": {
            "name_station": "Царицыно МЦД-2",
            "name_line": "Д2",
            "id": "322",
            "id_line": "17"
        }
    },
    {
        "model": "metro.Station",
        "pk": 360,
        "fields": {
            "name_station": "Покровское МЦД-2",
            "name_line": "Д2",
            "id": "323",
            "id_line": "17"
        }
    },
    {
        "model": "metro.Station",
        "pk": 361,
        "fields": {
            "name_station": "Красный Строитель МЦД-2",
            "name_line": "Д2",
            "id": "324",
            "id_line": "17"
        }
    },
    {
        "model": "metro.Station",
        "pk": 362,
        "fields": {
            "name_station": "Битца МЦД-2",
            "name_line": "Д2",
            "id": "325",
            "id_line": "17"
        }
    },
    {
        "model": "metro.Station",
        "pk": 363,
        "fields": {
            "name_station": "Бутово МЦД-2",
            "name_line": "Д2",
            "id": "326",
            "id_line": "17"
        }
    },
    {
        "model": "metro.Station",
        "pk": 364,
        "fields": {
            "name_station": "Щербинка МЦД-2",
            "name_line": "Д2",
            "id": "327",
            "id_line": "17"
        }
    },
    {
        "model": "metro.Station",
        "pk": 365,
        "fields": {
            "name_station": "Остафьево МЦД-2",
            "name_line": "Д2",
            "id": "328",
            "id_line": "17"
        }
    },
    {
        "model": "metro.Station",
        "pk": 366,
        "fields": {
            "name_station": "Силикатная МЦД-2(П)",
            "name_line": "Д2",
            "id": "329",
            "id_line": "17"
        }
    },
    {
        "model": "metro.Station",
        "pk": 367,
        "fields": {
            "name_station": "Подольск МЦД-2(П)",
            "name_line": "Д2",
            "id": "330",
            "id_line": "17"
        }
    },
    {
        "model": "metro.Station",
        "pk": 368,
        "fields": {
            "name_station": "Крюково МЦД-3 (П)",
            "name_line": "Д3",
            "id": "367",
            "id_line": "18"
        }
    },
    {
        "model": "metro.Station",
        "pk": 369,
        "fields": {
            "name_station": "Фирсановская МЦД-3(П)",
            "name_line": "Д3",
            "id": "369",
            "id_line": "18"
        }
    },
    {
        "model": "metro.Station",
        "pk": 370,
        "fields": {
            "name_station": "Сходня МЦД-3(П)",
            "name_line": "Д3",
            "id": "370",
            "id_line": "18"
        }
    },
    {
        "model": "metro.Station",
        "pk": 371,
        "fields": {
            "name_station": "Подрезково МЦД-3(П)",
            "name_line": "Д3",
            "id": "371",
            "id_line": "18"
        }
    },
    {
        "model": "metro.Station",
        "pk": 372,
        "fields": {
            "name_station": "Новоподрезково МЦД-3(П)",
            "name_line": "Д3",
            "id": "372",
            "id_line": "18"
        }
    },
    {
        "model": "metro.Station",
        "pk": 373,
        "fields": {
            "name_station": "Молжаниново МЦД-3(П)",
            "name_line": "Д3",
            "id": "373",
            "id_line": "18"
        }
    },
    {
        "model": "metro.Station",
        "pk": 374,
        "fields": {
            "name_station": "Химки МЦД-3(П)",
            "name_line": "Д3",
            "id": "374",
            "id_line": "18"
        }
    },
    {
        "model": "metro.Station",
        "pk": 375,
        "fields": {
            "name_station": "Левобережная МЦД-3(П)",
            "name_line": "Д3",
            "id": "375",
            "id_line": "18"
        }
    },
    {
        "model": "metro.Station",
        "pk": 376,
        "fields": {
            "name_station": "Ховрино МЦД-3",
            "name_line": "Д3",
            "id": "376",
            "id_line": "18"
        }
    },
    {
        "model": "metro.Station",
        "pk": 377,
        "fields": {
            "name_station": "Грачёвская МЦД-3",
            "name_line": "Д3",
            "id": "377",
            "id_line": "18"
        }
    },
    {
        "model": "metro.Station",
        "pk": 378,
        "fields": {
            "name_station": "Моссельмаш МЦД-3",
            "name_line": "Д3",
            "id": "378",
            "id_line": "18"
        }
    },
    {
        "model": "metro.Station",
        "pk": 379,
        "fields": {
            "name_station": "Лихоборы МЦД-3",
            "name_line": "Д3",
            "id": "379",
            "id_line": "18"
        }
    },
    {
        "model": "metro.Station",
        "pk": 380,
        "fields": {
            "name_station": "Петровско-Разумовская МЦД-3",
            "name_line": "Д3",
            "id": "380",
            "id_line": "18"
        }
    },
    {
        "model": "metro.Station",
        "pk": 381,
        "fields": {
            "name_station": "Останкино МЦД-3",
            "name_line": "Д3",
            "id": "381",
            "id_line": "18"
        }
    },
    {
        "model": "metro.Station",
        "pk": 382,
        "fields": {
            "name_station": "Электрозаводская МЦД-3",
            "name_line": "Д3",
            "id": "384",
            "id_line": "18"
        }
    },
    {
        "model": "metro.Station",
        "pk": 383,
        "fields": {
            "name_station": "Сортировочная МЦД-3",
            "name_line": "Д3",
            "id": "385",
            "id_line": "18"
        }
    },
    {
        "model": "metro.Station",
        "pk": 384,
        "fields": {
            "name_station": "Авиамоторная МЦД-3",
            "name_line": "Д3",
            "id": "386",
            "id_line": "18"
        }
    },
    {
        "model": "metro.Station",
        "pk": 385,
        "fields": {
            "name_station": "Андроновка МЦД-3",
            "name_line": "Д3",
            "id": "387",
            "id_line": "18"
        }
    },
    {
        "model": "metro.Station",
        "pk": 386,
        "fields": {
            "name_station": "Перово МЦД-3",
            "name_line": "Д3",
            "id": "388",
            "id_line": "18"
        }
    },
    {
        "model": "metro.Station",
        "pk": 387,
        "fields": {
            "name_station": "Плющево МЦД-3",
            "name_line": "Д3",
            "id": "389",
            "id_line": "18"
        }
    },
    {
        "model": "metro.Station",
        "pk": 388,
        "fields": {
            "name_station": "Вешняки МЦД-3",
            "name_line": "Д3",
            "id": "390",
            "id_line": "18"
        }
    },
    {
        "model": "metro.Station",
        "pk": 389,
        "fields": {
            "name_station": "Выхино МЦД-3",
            "name_line": "Д3",
            "id": "391",
            "id_line": "18"
        }
    },
    {
        "model": "metro.Station",
        "pk": 390,
        "fields": {
            "name_station": "Косино МЦД-3",
            "name_line": "Д3",
            "id": "392",
            "id_line": "18"
        }
    },
    {
        "model": "metro.Station",
        "pk": 391,
        "fields": {
            "name_station": "Ухтомская МЦД-3",
            "name_line": "Д3",
            "id": "393",
            "id_line": "18"
        }
    },
    {
        "model": "metro.Station",
        "pk": 392,
        "fields": {
            "name_station": "Люберцы МЦД-3(П)",
            "name_line": "Д3",
            "id": "394",
            "id_line": "18"
        }
    },
    {
        "model": "metro.Station",
        "pk": 393,
        "fields": {
            "name_station": "Панки МЦД-3(П)",
            "name_line": "Д3",
            "id": "395",
            "id_line": "18"
        }
    },
    {
        "model": "metro.Station",
        "pk": 394,
        "fields": {
            "name_station": "Томилино МЦД3(П)",
            "name_line": "Д3",
            "id": "396",
            "id_line": "18"
        }
    },
    {
        "model": "metro.Station",
        "pk": 395,
        "fields": {
            "name_station": "Красково МЦД-3(П)",
            "name_line": "Д3",
            "id": "397",
            "id_line": "18"
        }
    },
    {
        "model": "metro.Station",
        "pk": 396,
        "fields": {
            "name_station": "Малаховка МЦД-3(П)",
            "name_line": "Д3",
            "id": "398",
            "id_line": "18"
        }
    },
    {
        "model": "metro.Station",
        "pk": 397,
        "fields": {
            "name_station": "Удельная МЦД-3(П)",
            "name_line": "Д3",
            "id": "399",
            "id_line": "18"
        }
    },
    {
        "model": "metro.Station",
        "pk": 398,
        "fields": {
            "name_station": "Быково МЦД-3(П)",
            "name_line": "Д3",
            "id": "400",
            "id_line": "18"
        }
    },
    {
        "model": "metro.Station",
        "pk": 399,
        "fields": {
            "name_station": "Ильинская МЦД-3(П)",
            "name_line": "Д3",
            "id": "401",
            "id_line": "18"
        }
    },
    {
        "model": "metro.Station",
        "pk": 400,
        "fields": {
            "name_station": "Отдых МЦД-3(П)",
            "name_line": "Д3",
            "id": "402",
            "id_line": "18"
        }
    },
    {
        "model": "metro.Station",
        "pk": 401,
        "fields": {
            "name_station": "Кратово МЦД-3(П)",
            "name_line": "Д3",
            "id": "403",
            "id_line": "18"
        }
    },
    {
        "model": "metro.Station",
        "pk": 402,
        "fields": {
            "name_station": "Есенинская МЦД-3(П)",
            "name_line": "Д3",
            "id": "404",
            "id_line": "18"
        }
    },
    {
        "model": "metro.Station",
        "pk": 403,
        "fields": {
            "name_station": "Фабричная МЦД-3(П)",
            "name_line": "Д3",
            "id": "405",
            "id_line": "18"
        }
    },
    {
        "model": "metro.Station",
        "pk": 404,
        "fields": {
            "name_station": "Раменское МЦД-3(П)",
            "name_line": "Д3",
            "id": "406",
            "id_line": "18"
        }
    },
    {
        "model": "metro.Station",
        "pk": 405,
        "fields": {
            "name_station": "Ипподром МЦД-3(П)",
            "name_line": "Д3",
            "id": "407",
            "id_line": "18"
        }
    },
    {
        "model": "metro.Station",
        "pk": 406,
        "fields": {
            "name_station": "Железнодорожная МЦД-4(П)",
            "name_line": "Д4",
            "id": "413",
            "id_line": "19"
        }
    },
    {
        "model": "metro.Station",
        "pk": 407,
        "fields": {
            "name_station": "Ольгино МЦД-4(П)",
            "name_line": "Д4",
            "id": "414",
            "id_line": "19"
        }
    },
    {
        "model": "metro.Station",
        "pk": 408,
        "fields": {
            "name_station": "Кучино МЦД-4(П)",
            "name_line": "Д4",
            "id": "415",
            "id_line": "19"
        }
    },
    {
        "model": "metro.Station",
        "pk": 409,
        "fields": {
            "name_station": "Салтыковская МЦД-4(П)",
            "name_line": "Д4",
            "id": "416",
            "id_line": "19"
        }
    },
    {
        "model": "metro.Station",
        "pk": 410,
        "fields": {
            "name_station": "Никольское МЦД-4(П)",
            "name_line": "Д4",
            "id": "417",
            "id_line": "19"
        }
    },
    {
        "model": "metro.Station",
        "pk": 411,
        "fields": {
            "name_station": "Реутов МЦД-4",
            "name_line": "Д4",
            "id": "418",
            "id_line": "19"
        }
    },
    {
        "model": "metro.Station",
        "pk": 412,
        "fields": {
            "name_station": "Новогиреево МЦД-4",
            "name_line": "Д4",
            "id": "419",
            "id_line": "19"
        }
    },
    {
        "model": "metro.Station",
        "pk": 413,
        "fields": {
            "name_station": "Кусково МЦД-4",
            "name_line": "Д4",
            "id": "420",
            "id_line": "19"
        }
    },
    {
        "model": "metro.Station",
        "pk": 414,
        "fields": {
            "name_station": "Чухлинка МЦД-4",
            "name_line": "Д4",
            "id": "421",
            "id_line": "19"
        }
    },
    {
        "model": "metro.Station",
        "pk": 415,
        "fields": {
            "name_station": "Нижегородская МЦД-4",
            "name_line": "Д4",
            "id": "422",
            "id_line": "19"
        }
    },
    {
        "model": "metro.Station",
        "pk": 416,
        "fields": {
            "name_station": "Серп и Молот МЦД-4",
            "name_line": "Д4",
            "id": "423",
            "id_line": "19"
        }
    },
    {
        "model": "metro.Station",
        "pk": 417,
        "fields": {
            "name_station": "Курская МЦД-4",
            "name_line": "Д4",
            "id": "424",
            "id_line": "19"
        }
    },
    {
        "model": "metro.Station",
        "pk": 418,
        "fields": {
            "name_station": "Площадь трёх вокзалов МЦД-4",
            "name_line": "Д4",
            "id": "425",
            "id_line": "19"
        }
    },
    {
        "model": "metro.Station",
        "pk": 419,
        "fields": {
            "name_station": "Марьина Роща МЦД-4",
            "name_line": "Д4",
            "id": "426",
            "id_line": "19"
        }
    },
    {
        "model": "metro.Station",
        "pk": 420,
        "fields": {
            "name_station": "Савеловская МЦД-4",
            "name_line": "Д4",
            "id": "427",
            "id_line": "19"
        }
    },
    {
        "model": "metro.Station",
        "pk": 421,
        "fields": {
            "name_station": "Белорусская МЦД-4",
            "name_line": "Д4",
            "id": "428",
            "id_line": "19"
        }
    },
    {
        "model": "metro.Station",
        "pk": 422,
        "fields": {
            "name_station": "Тестовская (Москва-Сити) МЦД-4",
            "name_line": "Д4",
            "id": "451",
            "id_line": "19"
        }
    },
    {
        "model": "metro.Station",
        "pk": 423,
        "fields": {
            "name_station": "Кутузовская МЦД-4",
            "name_line": "Д4",
            "id": "430",
            "id_line": "19"
        }
    },
    {
        "model": "metro.Station",
        "pk": 424,
        "fields": {
            "name_station": "Поклонная МЦД-4",
            "name_line": "Д4",
            "id": "431",
            "id_line": "19"
        }
    },
    {
        "model": "metro.Station",
        "pk": 425,
        "fields": {
            "name_station": "Минская МЦД-4",
            "name_line": "Д4",
            "id": "432",
            "id_line": "19"
        }
    },
    {
        "model": "metro.Station",
        "pk": 426,
        "fields": {
            "name_station": "Матвеевская МЦД-4",
            "name_line": "Д4",
            "id": "433",
            "id_line": "19"
        }
    },
    {
        "model": "metro.Station",
        "pk": 427,
        "fields": {
            "name_station": "Аминьевская МЦД-4",
            "name_line": "Д4",
            "id": "434",
            "id_line": "19"
        }
    },
    {
        "model": "metro.Station",
        "pk": 428,
        "fields": {
            "name_station": "Очаково МЦД-4",
            "name_line": "Д4",
            "id": "435",
            "id_line": "19"
        }
    },
    {
        "model": "metro.Station",
        "pk": 429,
        "fields": {
            "name_station": "Мещерская МЦД-4",
            "name_line": "Д4",
            "id": "436",
            "id_line": "19"
        }
    },
    {
        "model": "metro.Station",
        "pk": 430,
        "fields": {
            "name_station": "Солнечная МЦД-4",
            "name_line": "Д4",
            "id": "437",
            "id_line": "19"
        }
    },
    {
        "model": "metro.Station",
        "pk": 431,
        "fields": {
            "name_station": "Переделкино МЦД-4",
            "name_line": "Д4",
            "id": "438",
            "id_line": "19"
        }
    },
    {
        "model": "metro.Station",
        "pk": 432,
        "fields": {
            "name_station": "Мичуринец МЦД-4",
            "name_line": "Д4",
            "id": "439",
            "id_line": "19"
        }
    },
    {
        "model": "metro.Station",
        "pk": 433,
        "fields": {
            "name_station": "Внуково МЦД-4",
            "name_line": "Д4",
            "id": "440",
            "id_line": "19"
        }
    },
    {
        "model": "metro.Station",
        "pk": 434,
        "fields": {
            "name_station": "Лесной Городок МЦД-4(П)",
            "name_line": "Д4",
            "id": "441",
            "id_line": "19"
        }
    },
    {
        "model": "metro.Station",
        "pk": 435,
        "fields": {
            "name_station": "Толстопальцево МЦД-4(П)",
            "name_line": "Д4",
            "id": "442",
            "id_line": "19"
        }
    },
    {
        "model": "metro.Station",
        "pk": 436,
        "fields": {
            "name_station": "Кокошкино МЦД-4(П)",
            "name_line": "Д4",
            "id": "443",
            "id_line": "19"
        }
    },
    {
        "model": "metro.Station",
        "pk": 437,
        "fields": {
            "name_station": "Санино МЦД-4(П)",
            "name_line": "Д4",
            "id": "444",
            "id_line": "19"
        }
    },
    {
        "model": "metro.Station",
        "pk": 438,
        "fields": {
            "name_station": "Крёкшино МЦД-4(П)",
            "name_line": "Д4",
            "id": "445",
            "id_line": "19"
        }
    },
    {
        "model": "metro.Station",
        "pk": 439,
        "fields": {
            "name_station": "Победа МЦД-4(П)",
            "name_line": "Д4",
            "id": "446",
            "id_line": "19"
        }
    },
    {
        "model": "metro.Station",
        "pk": 440,
        "fields": {
            "name_station": "Апрелевка МЦД-4(П)",
            "name_line": "Д4",
            "id": "447",
            "id_line": "19"
        }
    }
]